airton_ac/__init__.py
airton_ac/device.py
airton_ac/domoticz/__init__.py
airton_ac/domoticz/install.py
airton_ac/py.typed
airton_ac-3.0.0.dist-info/LICENSE
airton_ac-3.0.0.dist-info/METADATA
airton_ac-3.0.0.dist-info/WHEEL
airton_ac-3.0.0.dist-info/RECORD
