Metadata-Version: 2.1
Name: airton_ac
Version: 3.0.0
Summary: Control an Airton AC device over LAN.
Home-page: https://github.com/gpajot/airton-ac
License: MIT
Author: Gabriel Pajot
Author-email: gab@les-cactus.co
Requires-Python: >=3.8
Classifier: License :: OSI Approved :: MIT License
Classifier: Programming Language :: Python :: 3
Classifier: Programming Language :: Python :: 3.8
Classifier: Programming Language :: Python :: 3.9
Classifier: Programming Language :: Python :: 3.10
Classifier: Programming Language :: Python :: 3.11
Classifier: Programming Language :: Python :: 3.12
Provides-Extra: domoticz
Requires-Dist: local-tuya (>=3,<4)
Requires-Dist: local-tuya-domoticz-tools (>=1.2,<2) ; extra == "domoticz"
Project-URL: Repository, https://github.com/gpajot/airton-ac
